nncli/__init__.py
nncli/__main__.py
nncli/cli.py
nncli/clipboard.py
nncli/config.py
nncli/gui.py
nncli/log.py
nncli/nextcloud_note.py
nncli/nncli.py
nncli/notes_db.py
nncli/temp.py
nncli/user_input.py
nncli/utils.py
nncli/view_help.py
nncli/view_log.py
nncli/view_note.py
nncli/view_titles.py
nncli-0.3.8.dist-info/entry_points.txt
nncli-0.3.8.dist-info/WHEEL
nncli-0.3.8.dist-info/METADATA
nncli-0.3.8.dist-info/RECORD
