Metadata-Version: 2.1
Name: nncli
Version: 0.3.8
Summary: NextCloud Notes Command Line Interface
Author-email: Daniel Moch <daniel@danielmoch.com>
Requires-Python: >=3.9
Classifier: License :: OSI Approved :: MIT License
Classifier: Development Status :: 4 - Beta
Classifier: Environment :: Console :: Curses
Classifier: Intended Audience :: End Users/Desktop
Classifier: License :: OSI Approved :: MIT License
Classifier: Programming Language :: Python :: 3 :: Only
Requires-Dist: appdirs
Requires-Dist: click
Requires-Dist: requests
Requires-Dist: urwid
Requires-Dist: flit ; extra == "dev"
Requires-Dist: mock ; extra == "dev"
Requires-Dist: pathlib2 ; extra == "dev" and ( python_version < '3.5')
Requires-Dist: pip-tools ; extra == "dev"
Requires-Dist: pylint ; extra == "dev"
Requires-Dist: pytest-cov ; extra == "dev"
Requires-Dist: pytest-mock ; extra == "dev"
Requires-Dist: pytest>=6.2.5 ; extra == "dev"
Requires-Dist: scandir ; extra == "dev" and ( python_version < '3.5')
Requires-Dist: sphinx ; extra == "dev"
Requires-Dist: sphinx-material ; extra == "dev"
Requires-Dist: sphinx-sitemap ; extra == "dev"
Requires-Dist: vulture ; extra == "dev"
Requires-Dist: sphinx ; extra == "doc"
Requires-Dist: sphinx-material ; extra == "doc"
Requires-Dist: sphinx-sitemap ; extra == "doc"
Project-URL: Homepage, https://nncli.org
Project-URL: Source Code, https://github.com/djmoch/nncli
Provides-Extra: dev
Provides-Extra: doc
